    {
      "name": "Roam References Radar",
      "short_description": "A Roam Research plugin that helps you discover more potential connections in your knowledge graph by identifying and suggesting relevant references.",
      "author": "hyc",
      "source_url": "https://github.com/dive2Pro/roam-references-radar",
      "source_repo": "https://github.com/dive2Pro/roam-references-radar.git",
      "source_commit": "d8ca356864f9b579334123e08301732d6ccd1ffe",
      "stripe_account": "acct_1LLkJkQbYbNOfzpa"
    }            
