{
	"name": "Export Formatter",
	"short_description": "Adds a context menu option to export the selected node with various formatting options, such as removing roam specific syntax, making it suitable to share in emails, slack or other places. A port of my previous project: https://roam-tools.ryanguill.com / https://github.com/ryanguill/roam-tools",
	"author": "Ryan Guill",
	"tags": ["export", "formatting"],
	"source_url": "https://github.com/ryanguill/roam-depot-export-formatter",
	"source_repo": "https://github.com/ryanguill/roam-depot-export-formatter.git",
	"source_commit": "bd09b5bdf4a4beac674a7f868c00dacac9b25013",
	"stripe_account": "acct_1Le7xkQmgYSLp29w"
  }
