{
  "name": "Find & Replace",
  "short_description": "Way more than Find & Replace: also Search in page or graph (with Regex), bulk operations (format, clean, case change, append/prepend, extract, page names changes...) and Block <=> Page conversion.",
  "author": "Fabrice Gallet",
  "tags": ["productivity", "regex", "search", "bulk", "prepend", "append"],
  "source_url": "https://github.com/fbgallet/roam-extension-find-replace",
  "source_repo": "https://github.com/fbgallet/roam-extension-find-replace.git",
  "source_commit": "d483486df936de6427be9f7d382682544423ce98",
  "stripe_account": "acct_1LJHuRQerhPsAmG6"
}
