{
  "name": "Yesterday & Tomorrow",
  "short_description": "Add buttons to the Roam Top Bar with shortcuts to Yesterday, Today and Tomorrow. Or, use perpetual mode to allow backward or forward navigation through your DNPs.",
  "author": "Mark Lavercombe",
  "tags": ["buttons"],
  "source_url": "https://github.com/mlava/yesterday-tomorrow",
  "source_repo": "https://github.com/mlava/yesterday-tomorrow.git",
  "source_commit": "67aab8bbe0308a328155d12508bdba8f4508a6e9",
  "stripe_account": "acct_1LNVRQQVHUZMIiOR"
}
